lib_compare_packages/__init__.py
lib_compare_packages/cli.py
lib_compare_packages/lib_compare_packages.py
lib_compare_packages-0.1.dist-info/METADATA
lib_compare_packages-0.1.dist-info/WHEEL
lib_compare_packages-0.1.dist-info/entry_points.txt
lib_compare_packages-0.1.dist-info/top_level.txt
lib_compare_packages-0.1.dist-info/RECORD
