Metadata-Version: 2.1
Name: lib-compare-packages
Version: 0.1
Summary: library for comparing two branches
Home-page: https://github.com/aksalena/lib_compare_packages
Author: Alena Guseva
Author-email: axenova.ale@mail.ru
Classifier: Programming Language :: Python :: 3
Classifier: License :: OSI Approved :: MIT License
Requires-Dist: requests
